jgtapy/__init__.py
jgtapy/indicators.py
jgtapy/utils.py
jgtapy-1.9.22.dist-info/licenses/LICENSE
jgtapy-1.9.22.dist-info/METADATA
jgtapy-1.9.22.dist-info/WHEEL
jgtapy-1.9.22.dist-info/top_level.txt
jgtapy-1.9.22.dist-info/RECORD
