Metadata-Version: 2.4
Name: jgtapy
Version: 1.9.22
Summary: Enhanced JGTapy
Home-page: https://github.com/jgwill/jgtapy
Author: Dmitrii Kurlov/(forked:JGWill)
Author-email: JGWill <jgi@jgwill.com>
Project-URL: Homepage, https://jgtapy.jgwill.com
Project-URL: Bug Tracker, https://github.com/jgwill/jgtapy/issues
Classifier: Programming Language :: Python :: 3
Classifier: License :: OSI Approved :: MIT License
Classifier: Operating System :: OS Independent
Requires-Python: >=3.7
License-File: LICENSE
Dynamic: author
Dynamic: home-page
Dynamic: license-file
